streaming_xml_parser-1.0.0.dist-info/licenses/LICENSE
xmlstream/__init__.py
xmlstream/behaviors.py
xmlstream/config.py
xmlstream/core.py
xmlstream/events.py
xmlstream/exceptions.py
xmlstream/handlers.py
xmlstream/py.typed
streaming_xml_parser-1.0.0.dist-info/METADATA
streaming_xml_parser-1.0.0.dist-info/WHEEL
streaming_xml_parser-1.0.0.dist-info/top_level.txt
streaming_xml_parser-1.0.0.dist-info/RECORD
