Metadata-Version: 2.4
Name: streaming-xml-parser
Version: 1.0.0
Summary: High-performance streaming XML parser for real-time applications
Home-page: https://github.com/AgnostechAI/xmlstream
Author: Agnostech
Author-email: Ravi Raina <ravi@agnostech.ca>
Maintainer-email: Ravi Raina <ravi@agnostech.ca>
License: MIT
Project-URL: Homepage, https://github.com/AgnostechAI/xmlstream
Project-URL: Documentation, https://github.com/AgnostechAI/xmlstream/README.md
Project-URL: Repository, https://github.com/AgnostechAI/xmlstream.git
Project-URL: Bug Tracker, https://github.com/xmlstream/xmlstream/issues
Project-URL: Changelog, https://github.com/xmlstream/xmlstream/blob/main/CHANGELOG.md
Keywords: xml,parser,streaming,real-time,performance,llm
Classifier: Development Status :: 4 - Beta
Classifier: Intended Audience :: Developers
Classifier: Topic :: Software Development :: Libraries :: Python Modules
Classifier: Topic :: Text Processing :: Markup :: XML
Classifier: License :: OSI Approved :: MIT License
Classifier: Programming Language :: Python :: 3
Classifier: Programming Language :: Python :: 3.8
Classifier: Programming Language :: Python :: 3.9
Classifier: Programming Language :: Python :: 3.10
Classifier: Programming Language :: Python :: 3.11
Classifier: Programming Language :: Python :: 3.12
Classifier: Operating System :: OS Independent
Classifier: Typing :: Typed
Requires-Python: >=3.8
License-File: LICENSE
Provides-Extra: dev
Requires-Dist: pytest>=6.0.0; extra == "dev"
Requires-Dist: pytest-cov>=2.0.0; extra == "dev"
Requires-Dist: black>=21.0.0; extra == "dev"
Requires-Dist: flake8>=3.8.0; extra == "dev"
Requires-Dist: mypy>=0.800; extra == "dev"
Requires-Dist: isort>=5.0.0; extra == "dev"
Provides-Extra: docs
Requires-Dist: sphinx>=3.0.0; extra == "docs"
Requires-Dist: sphinx-rtd-theme>=0.5.0; extra == "docs"
Requires-Dist: myst-parser>=0.15.0; extra == "docs"
Provides-Extra: test
Requires-Dist: pytest>=6.0.0; extra == "test"
Requires-Dist: pytest-cov>=2.0.0; extra == "test"
Requires-Dist: pytest-benchmark>=3.4.0; extra == "test"
Dynamic: author
Dynamic: home-page
Dynamic: license-file
Dynamic: requires-python
